mcpdoc/__init__.py
mcpdoc/_version.py
mcpdoc/cli.py
mcpdoc/langgraph.py
mcpdoc/main.py
mcpdoc/splash.py
mcpdoc-0.0.10.dist-info/METADATA
mcpdoc-0.0.10.dist-info/WHEEL
mcpdoc-0.0.10.dist-info/entry_points.txt
mcpdoc-0.0.10.dist-info/licenses/LICENSE
mcpdoc-0.0.10.dist-info/RECORD
